setup.cfg
setup.py
keyword_tree.egg-info/PKG-INFO
keyword_tree.egg-info/SOURCES.txt
keyword_tree.egg-info/dependency_links.txt
keyword_tree.egg-info/not-zip-safe
keyword_tree.egg-info/requires.txt
keyword_tree.egg-info/top_level.txt
keywordtree/__init__.py
keywordtree/keywordtree.py
keywordtree/tests.py