Metadata-Version: 1.0
Name: keyword-tree
Version: 0.5.1
Summary: Data-structure for keyword searches
Home-page: https://dpettifor.crc.nd.edu/software/keyword_tree/
Author: David W Pettifor
Author-email: dpettifo@nd.edu
License: GPL-3.0
Keywords: keyword,tree
Platform: UNKNOWN
